django_cacheable_model/__init__.py
django_cacheable_model/models.py
django_cacheable_model/utils.py
django_cacheable_model-1.2.7.dist-info/LICENSE
django_cacheable_model-1.2.7.dist-info/METADATA
django_cacheable_model-1.2.7.dist-info/WHEEL
django_cacheable_model-1.2.7.dist-info/top_level.txt
django_cacheable_model-1.2.7.dist-info/RECORD
