Metadata-Version: 2.1
Name: django_cacheable_model
Version: 1.2.7
Summary: A cacheable Django model
Author-email: "Harisankar Krishna Swamy @ Vevde" <harisankar.krishna@outlook.com>
Project-URL: Homepage, https://github.com/harisankar-krishna-swamy/django_cacheable_model.git
Classifier: Programming Language :: Python :: 3
Classifier: License :: OSI Approved :: Apache Software License
Classifier: Operating System :: OS Independent
Requires-Python: >=3.7.4
License-File: LICENSE
Requires-Dist: Django >=2.0
